{
  "timestamp": 1783909034,
  "commit": "80ad0b8c7527098c9ab304f239ebfde2f69332dd",
  "contract_digest": "226818144c72776a418d082a177824e0ea1cc390b5b1ad33f79e2136ae00af98",
  "workspace_digest": "e75b85fceb98c84ce3fae733bca2d78c82617e795349f64366a9cee2aef18e34",
  "passed": true,
  "commands": [
    {
      "command": "swift test",
      "success": true,
      "exit_code": 0
    },
    {
      "command": "bash Tests/action_contract_test.sh",
      "success": true,
      "exit_code": 0
    }
  ],
  "requirement_ids": [
    "REQ-attest-action-001",
    "REQ-attest-action-002",
    "REQ-attest-action-003"
  ]
}
